delight/__init__.py
delight/data/__init__.py
delight/data/collector.py
delight/data/replay/__init__.py
delight/data/replay/core.py
delight/data/replay/simple.py
delight/data/transforms/__init__.py
delight/data/transforms/augment.py
delight/data/transforms/common.py
delight/data/transforms/conversion.py
delight/envs/__init__.py
delight/envs/_dm_patch.py
delight/envs/atari.py
delight/envs/dm_control.py
delight/envs/ray_env.py
delight/envs/vec_env.py
delight/envs/wrappers.py
delight/envs/gibson/__init__.py
delight/envs/gibson/basic.py
delight/envs/gibson/nav.py
delight/envs/gibson/wrappers.py
delight/envs/gibson/config/__init__.py
delight/exp/__init__.py
delight/exp/acme.py
delight/legacy/__init__.py
delight/legacy/data/__init__.py
delight/legacy/data/collector.py
delight/legacy/data/replay.py
delight/legacy/data/replay_aug.py
delight/legacy/rl/__init__.py
delight/legacy/rl/distributions.py
delight/legacy/rl/algo/__init__.py
delight/legacy/rl/algo/sac.py
delight/model/__init__.py
delight/model/ars.py
delight/model/backbone.py
delight/model/dm_control.py
delight/model/gibson.py
delight/model/linear_control.py
delight/model/offline.py
delight/model/video_net.py
delight/rl/__init__.py
delight/rl/distributions.py
delight/rl/algo/__init__.py
delight/rl/algo/sac.py
delight/rl/algo/sac_selfsup.py
delight/rl/ars/__init__.py
delight/rl/ars/learner.py
delight/rl/ars/shared_noise.py
delight/rl/ars/shared_space.py
delight/utils/__init__.py
delight/utils/logger.py
delight/utils/torch_utils.py
enlight/__init__.py
enlight/data/__init__.py
enlight/data/collector.py
enlight/data/iterable_dataset.py
enlight/data/replay.py
enlight/data/replay_aug.py
enlight/envs/__init__.py
enlight/envs/_dm_patch.py
enlight/envs/atari.py
enlight/envs/dm_control.py
enlight/envs/vec_env.py
enlight/envs/wrappers.py
enlight/model/__init__.py
enlight/model/backbone.py
enlight/model/dm_control.py
enlight/rl/__init__.py
enlight/rl/distributions.py
enlight/rl/algo/__init__.py
enlight/rl/algo/sac.py
delight-0.1.post1.dist-info/LICENSE
delight-0.1.post1.dist-info/METADATA
delight-0.1.post1.dist-info/WHEEL
delight-0.1.post1.dist-info/entry_points.txt
delight-0.1.post1.dist-info/top_level.txt
delight-0.1.post1.dist-info/RECORD
